<?xml version="1.0" encoding="utf-8" ?><dwsync><file name="april.jpg" server="www.sugarmobile.ca//" local="3555157636" remote="3570993480" Dst="-1" /><file name="december.jpg" server="www.sugarmobile.ca//" local="3555157636" remote="3570993480" Dst="-1" /><file name="august.jpg" server="www.sugarmobile.ca//" local="3555157636" remote="3570993480" Dst="-1" /><file name="july.jpg" server="www.sugarmobile.ca//" local="3555157636" remote="3570993480" Dst="-1" /><file name="february.jpg" server="www.sugarmobile.ca//" local="3555157636" remote="3570993480" Dst="-1" /><file name="january.jpg" server="www.sugarmobile.ca//" local="3555157636" remote="3570993480" Dst="-1" /><file name="june.jpg" server="www.sugarmobile.ca//" local="3555157636" remote="3570993480" Dst="-1" /><file name="march.jpg" server="www.sugarmobile.ca//" local="3555157636" remote="3570993480" Dst="-1" /><file name="may.jpg" server="www.sugarmobile.ca//" local="3555157636" remote="3570993480" Dst="-1" /><file name="november.jpg" server="www.sugarmobile.ca//" local="3555157636" remote="3570993480" Dst="-1" /><file name="october.jpg" server="www.sugarmobile.ca//" local="3555157636" remote="3570993480" Dst="-1" /><file name="september.jpg" server="www.sugarmobile.ca//" local="3555157636" remote="3570993480" Dst="-1" /></dwsync>